AUTHORS.rst
CONTRIBUTING.rst
HISTORY.rst
LICENSE
MANIFEST.in
README.rst
setup.py
erepapi/__init__.py
erepapi/api.py
erepapi/battle.py
erepapi/citizen.py
erepapi/countries.py
erepapi/country_regions.py
erepapi/region.py
erepapi.egg-info/PKG-INFO
erepapi.egg-info/SOURCES.txt
erepapi.egg-info/dependency_links.txt
erepapi.egg-info/not-zip-safe
erepapi.egg-info/top_level.txt