Metadata-Version: 1.1
Name: erepapi
Version: 0.1.0
Summary: Unofficial python wrapper for erepublik api
Home-page: https://github.com/Nikola-K/erepapi
Author: Nikola Kovacevic
Author-email: nikolak@outlook.com
License: MIT
Keywords: erepapi
Platform: UNKNOWN
Classifier: Development Status :: 2 - Pre-Alpha
Classifier: Intended Audience :: Developers
Classifier: License :: OSI Approved :: MIT License
Classifier: Natural Language :: English
Classifier: Programming Language :: Python :: 2
Classifier: Programming Language :: Python :: 2.7
Classifier: Programming Language :: Python :: 3
Classifier: Programming Language :: Python :: 3.3
Classifier: Programming Language :: Python :: Implementation :: PyPy
